chunkrank/__init__.py
chunkrank/answerers.py
chunkrank/chunker.py
chunkrank/models.py
chunkrank/pipeline.py
chunkrank/ranker.py
chunkrank/registry/__init__.py
chunkrank/registry/model_registry.json
chunkrank/tokenizers.py
chunkrank/utils/__init__.py
chunkrank-0.2.4.dist-info/METADATA
chunkrank-0.2.4.dist-info/WHEEL
chunkrank-0.2.4.dist-info/licenses/LICENCE
chunkrank-0.2.4.dist-info/RECORD
