Metadata-Version: 2.4
Name: chunkrank
Version: 0.2.4
Summary: Model-aware text chunking and answer re-ranking for LLM pipelines. Automatically adapts chunk size to tokenizer and context window, then consolidates and ranks answers across chunks.
License: MIT
License-File: LICENCE
Author: Amit Nautiyal
Author-email: de.amit.nautiyal@gmail.com
Requires-Python: >=3.14,<4.0
Classifier: License :: OSI Approved :: MIT License
Classifier: Programming Language :: Python :: 3
Classifier: Programming Language :: Python :: 3.14
Requires-Dist: deptry (>=0.24.0,<0.25.0)
Requires-Dist: mypy (>=1.19.1,<2.0.0)
Requires-Dist: numpy (>=1.26)
Requires-Dist: rank-bm25 (>=0.2.2)
Requires-Dist: regex (>=2023.10.3)
Requires-Dist: ruff (>=0.14.10,<0.15.0)
Requires-Dist: scikit-learn (>=1.5)
Project-URL: Documentation, https://gitlab.com/gaafa/smart-chunks/-/blob/main/README.md
Project-URL: Issue Tracker, https://gitlab.com/gaafa/smart-chunks/-/issues
Project-URL: Source Code, https://gitlab.com/gaafa/smart-chunks
